angular_gettext_babel-0.3.dist-info/METADATA
angular_gettext_babel-0.3.dist-info/DESCRIPTION.rst
angular_gettext_babel-0.3.dist-info/WHEEL
angular_gettext_babel-0.3.dist-info/pbr.json
angular_gettext_babel-0.3.dist-info/RECORD
angular_gettext_babel-0.3.dist-info/top_level.txt
angular_gettext_babel-0.3.dist-info/entry_points.txt
angular_gettext_babel-0.3.dist-info/metadata.json
angular_gettext_babel/__init__.py
angular_gettext_babel/extract.py
