Metadata-Version: 2.0
Name: angular-gettext-babel
Version: 0.3
Summary: A plugin for babel to work with angular-gettext templates
Home-page: https://github.com/neillc/angular-gettext-babel
Author: Neill Cox
Author-email: neill@ingenious.com.au
License: Apache Software License
Keywords: angular-gettext babel
Platform: UNKNOWN
Classifier: Development Status :: 3 - Alpha
Classifier: Intended Audience :: Developers
Classifier: Topic :: Software Development :: Internationalization
Classifier: License :: OSI Approved :: Apache Software License
Classifier: Programming Language :: Python :: 2
Classifier: Programming Language :: Python :: 2.7
Classifier: Programming Language :: Python :: 3
Classifier: Programming Language :: Python :: 3.2
Classifier: Programming Language :: Python :: 3.3
Classifier: Programming Language :: Python :: 3.4
Requires-Dist: babel
Provides-Extra: dev
Requires-Dist: check-manifest; extra == 'dev'
Provides-Extra: test
Requires-Dist: coverage; extra == 'test'
